{"current_page":1,"data":[{"id":"3d93450f-b57d-480b-a772-1001e33f21db","created_at":"2026-05-21T15:02:34.000000Z","updated_at":"2026-05-21T15:15:12.000000Z","user_id":"9e3ba817-660c-4fd2-a4ff-d6eee780ec43","package_id":"a1d551fa-6aa0-46ad-8982-d13e01a8a463","note":"\u6771\u6771\u7684\u98df\u7269","notify_state":"active","state":"inbox","pickup_reminder_flags":0,"package":{"id":"a1d551fa-6aa0-46ad-8982-d13e01a8a463","tracking_number":"TW265690897852R","carrier_id":"9a98100c-c984-463d-82a6-ae86ec4e0b8a","carrier":{"id":"9a98100c-c984-463d-82a6-ae86ec4e0b8a","name":"\u8766\u76ae\u5e97\u5230\u5e97"},"latest_package_history":{"id":"a1d551fc-22c8-464a-b859-00b34d437fc4","created_at":"2026-05-21T15:02:35.000000Z","updated_at":"2026-05-21T15:02:35.000000Z","package_id":"a1d551fa-6aa0-46ad-8982-d13e01a8a463","time":1779284638,"status":"\u5305\u88f9\u62b5\u9054\u71df\u696d\u6240\/\u670d\u52d9\u64da\u9ede","checkpoint_status":"transit","delivery_stage":"in_transit"}}}],"first_page_url":"https:\/\/track.tw\/api\/v1\/package\/all\/inbox?page=1","from":1,"last_page":1,"last_page_url":"https:\/\/track.tw\/api\/v1\/package\/all\/inbox?page=1","links":[{"url":null,"label":"&laquo; Previous","active":false},{"url":"https:\/\/track.tw\/api\/v1\/package\/all\/inbox?page=1","label":"1","active":true},{"url":null,"label":"Next &raquo;","active":false}],"next_page_url":null,"path":"https:\/\/track.tw\/api\/v1\/package\/all\/inbox","per_page":100,"prev_page_url":null,"to":1,"total":1,"counts":{"in_transit":1}}